gcumos/__init__.py
gcumos/logging.py
gcumos/metadata.py
gcumos/modeling.py
gcumos/pickler.py
gcumos/protogen.py
gcumos/session.py
gcumos/utils.py
gcumos/wrapped.py
gcumos-0.8.0.dist-info/METADATA
gcumos-0.8.0.dist-info/WHEEL
gcumos-0.8.0.dist-info/top_level.txt
gcumos-0.8.0.dist-info/RECORD
